metriport/__init__.py
metriport/client.py
metriport/core/__init__.py
metriport/core/api_error.py
metriport/core/client_wrapper.py
metriport/core/datetime_utils.py
metriport/core/jsonable_encoder.py
metriport/core/remove_none_from_dict.py
metriport/environment.py
metriport/py.typed
metriport/resources/__init__.py
metriport/resources/commons/__init__.py
metriport/resources/commons/types/__init__.py
metriport/resources/commons/types/address.py
metriport/resources/commons/types/us_state.py
metriport/resources/devices/__init__.py
metriport/resources/devices/client.py
metriport/resources/devices/resources/__init__.py
metriport/resources/devices/resources/connect/__init__.py
metriport/resources/devices/resources/connect/client.py
metriport/resources/devices/resources/users/__init__.py
metriport/resources/devices/resources/users/client.py
metriport/resources/devices/resources/users/types/__init__.py
metriport/resources/devices/resources/users/types/connect_token_response.py
metriport/resources/devices/resources/users/types/connected_providers_response.py
metriport/resources/devices/resources/users/types/delete_user_response.py
metriport/resources/devices/resources/users/types/metriport_user_id_response.py
metriport/resources/devices/resources/users/types/revoke_access_to_provider_response.py
metriport/resources/devices/types/__init__.py
metriport/resources/devices/types/activity.py
metriport/resources/devices/types/activity_durations.py
metriport/resources/devices/types/activity_log.py
metriport/resources/devices/types/activity_movement.py
metriport/resources/devices/types/activity_summary.py
metriport/resources/devices/types/aminos.py
metriport/resources/devices/types/biometrics.py
metriport/resources/devices/types/blood_oxygen.py
metriport/resources/devices/types/body.py
metriport/resources/devices/types/connected_user_info.py
metriport/resources/devices/types/duration.py
metriport/resources/devices/types/elevation.py
fern_metriport-0.1.8.dist-info/METADATA
fern_metriport-0.1.8.dist-info/WHEEL
fern_metriport-0.1.8.dist-info/RECORD
